ct/__init__.py
ct/__main__.py
ct/ct_global.py
ct/timer.py
ct/audio/110215__cheesepuff__a-soothing-song[CC0].ogg
ct/audio/110215__cheesepuff__a-soothing-song[CC0].wav
ct/audio/332932__bbatv__gentle-glockenspiel.ogg
ct/audio/332932__bbatv__gentle-glockenspiel.wav
ct/audio/415328__eardeer__slumberfoam.ogg
ct/audio/415328__eardeer__slumberfoam.wav
ct/gui/__init__.py
ct/gui/main_win.py
calm_timer-1.0.16a0.dist-info/LICENSE
calm_timer-1.0.16a0.dist-info/METADATA
calm_timer-1.0.16a0.dist-info/WHEEL
calm_timer-1.0.16a0.dist-info/entry_points.txt
calm_timer-1.0.16a0.dist-info/top_level.txt
calm_timer-1.0.16a0.dist-info/RECORD
