Metadata-Version: 2.1
Name: calm-timer
Version: 1.0.16a0
Summary: A simple timer application with some calm sounds to choose from
Home-page: https://gitlab.com/SunyataZero/calm-timer
Author: Tord Dellsén
Author-email: tord.dellsen@gmail.com
License: GPLv3
Platform: UNKNOWN
Classifier: License :: OSI Approved :: GNU General Public License v3 (GPLv3)
Classifier: Programming Language :: Python
Classifier: Programming Language :: Python :: 3
Requires-Python: >=3.0.0
Requires-Dist: PyQt5
Requires-Dist: pydub
